README.md
setup.py
shared_context/__init__.py
shared_context.egg-info/PKG-INFO
shared_context.egg-info/SOURCES.txt
shared_context.egg-info/dependency_links.txt
shared_context.egg-info/pbr.json
shared_context.egg-info/top_level.txt