Metadata-Version: 1.1
Name: shared-context
Version: 1.0.1
Summary: Shared tests between unittest TestCases
Home-page: https://github.com/younata/python_shared_context
Author: Rachel Brindle
Author-email: UNKNOWN
License: UNKNOWN
Keywords: unittest describe behaves like shared context
Platform: UNKNOWN
Classifier: License :: OSI Approved :: MIT License
Classifier: Programming Language :: Python :: 2
Classifier: Programming Language :: Python :: 2.7
Classifier: Programming Language :: Python :: 3
Classifier: Programming Language :: Python :: 3.5
Classifier: Programming Language :: Python :: 3.6
Classifier: Programming Language :: Python :: 3.7
